poetspy/generate.py
poetspy/poets.py
poetspy-0.2.0.dist-info/entry_points.txt
poetspy-0.2.0.dist-info/LICENSE
poetspy-0.2.0.dist-info/WHEEL
poetspy-0.2.0.dist-info/METADATA
poetspy-0.2.0.dist-info/RECORD
