Metadata-Version: 2.1
Name: poetspy
Version: 0.2.0
Summary: A small cli util to show project directories
Home-page: https://github.com/jokeneversoke/poets
License: MIT
Author: JokeNeverSoke
Author-email: zengjoseph@hotmail.com
Requires-Python: >=3.8,<4.0
Classifier: Development Status :: 3 - Alpha
Classifier: Intended Audience :: Developers
Classifier: License :: OSI Approved :: MIT License
Classifier: Programming Language :: Python :: 3
Classifier: Programming Language :: Python :: 3.10
Classifier: Programming Language :: Python :: 3.8
Classifier: Programming Language :: Python :: 3.9
Classifier: Topic :: Terminals
Classifier: Topic :: Utilities
Requires-Dist: click (>=8.0.0,<9.0.0)
Requires-Dist: loguru (>=0.5.3,<0.6.0)
Requires-Dist: marko (>=1.0.1,<2.0.0)
Requires-Dist: toml (>=0.10.2,<0.11.0)
